llmterm/__init__.py
llmterm/llms.py
llmterm/llmterm.py
llm_bash_helper-0.4.3.dist-info/METADATA
llm_bash_helper-0.4.3.dist-info/WHEEL
llm_bash_helper-0.4.3.dist-info/entry_points.txt
llm_bash_helper-0.4.3.dist-info/top_level.txt
llm_bash_helper-0.4.3.dist-info/RECORD
